musicalgestures/MusicalGesturesToolbox.ipynb
musicalgestures/__init__.py
musicalgestures/_audio.py
musicalgestures/_blend.py
musicalgestures/_blurfaces.py
musicalgestures/_centerface.py
musicalgestures/_colored.py
musicalgestures/_cropping_window.py
musicalgestures/_cropvideo.py
musicalgestures/_directograms.py
musicalgestures/_filter.py
musicalgestures/_flow.py
musicalgestures/_grid.py
musicalgestures/_history.py
musicalgestures/_impacts.py
musicalgestures/_info.py
musicalgestures/_input_test.py
musicalgestures/_mglist.py
musicalgestures/_motionanalysis.py
musicalgestures/_motionvideo.py
musicalgestures/_motionvideo_mp_render.py
musicalgestures/_motionvideo_mp_run.py
musicalgestures/_pose.py
musicalgestures/_show.py
musicalgestures/_show_window.py
musicalgestures/_ssm.py
musicalgestures/_subtract.py
musicalgestures/_utils.py
musicalgestures/_videoadjust.py
musicalgestures/_videograms.py
musicalgestures/_videoreader.py
musicalgestures/_warp.py
musicalgestures/3rdparty/windows/wget/wget.exe
musicalgestures/examples/Filtering.ipynb
musicalgestures/examples/dancer.avi
musicalgestures/examples/pianist.avi
musicalgestures/examples/test_dance.py
musicalgestures/examples/test_pianist.py
musicalgestures/models/centerface.onnx
musicalgestures/pose/getBODY_25_here.bat
musicalgestures/pose/getBODY_25_here.sh
musicalgestures/pose/getBODY_25_remote.bat
musicalgestures/pose/getBODY_25_remote.sh
musicalgestures/pose/getBODY_25_remote_colab.sh
musicalgestures/pose/getCOCO_here.bat
musicalgestures/pose/getCOCO_here.sh
musicalgestures/pose/getCOCO_remote.bat
musicalgestures/pose/getCOCO_remote.sh
musicalgestures/pose/getCOCO_remote_colab.sh
musicalgestures/pose/getMPI_here.bat
musicalgestures/pose/getMPI_here.sh
musicalgestures/pose/getMPI_remote.bat
musicalgestures/pose/getMPI_remote.sh
musicalgestures/pose/getMPI_remote_colab.sh
musicalgestures/pose/body_25/pose_deploy.prototxt
musicalgestures/pose/coco/pose_deploy_linevec.prototxt
musicalgestures-1.3.2.dist-info/LICENSE
musicalgestures-1.3.2.dist-info/METADATA
musicalgestures-1.3.2.dist-info/WHEEL
musicalgestures-1.3.2.dist-info/top_level.txt
musicalgestures-1.3.2.dist-info/RECORD
