Metadata-Version: 2.1
Name: musicalgestures
Version: 1.3.2
Summary: Musical Gestures Toolbox for Python
Home-page: https://github.com/fourMs/MGT-python
Author: University of Oslo fourMs Lab
Author-email: a.r.jensenius@imv.uio.no
License: GNU General Public License v3 (GPLv3)
Download-URL: https://github.com/fourMs/MGT-python/archive/v1.3.2.tar.gz
Keywords: Computer Vision,Motion Analysis,Musical Gestures,Video-Analysis
Platform: UNKNOWN
Classifier: Development Status :: 5 - Production/Stable
Classifier: Intended Audience :: Science/Research
Classifier: Topic :: Multimedia :: Video
Classifier: Topic :: Software Development :: Libraries :: Python Modules
Classifier: Topic :: Utilities
Classifier: License :: OSI Approved :: GNU General Public License v3 (GPLv3)
Classifier: Programming Language :: Python :: 3.7
Classifier: Programming Language :: Python :: 3.8
Requires-Python: ~=3.7
License-File: LICENSE
Requires-Dist: numpy
Requires-Dist: pandas
Requires-Dist: matplotlib
Requires-Dist: opencv-python
Requires-Dist: scipy
Requires-Dist: scikit-image
Requires-Dist: librosa
Requires-Dist: ipython (>=7.12)
